databricks_uniform_sync/__init__.py
databricks_uniform_sync/dbx_to_sf_mirror.py
databricks_uniform_sync/config/__init__.py
databricks_uniform_sync/config/logging_config.py
databricks_uniform_sync/data_models/__init__.py
databricks_uniform_sync/data_models/data_models.py
databricks_uniform_sync/logic/__init__.py
databricks_uniform_sync/logic/databricks/__init__.py
databricks_uniform_sync/logic/databricks/logic_uc_mapping.py
databricks_uniform_sync/logic/databricks/logic_uc_tags.py
databricks_uniform_sync/logic/metadata/__init__.py
databricks_uniform_sync/logic/metadata/metadata_mapping_logic.py
databricks_uniform_sync/logic/snowflake/__init__.py
databricks_uniform_sync/logic/snowflake/logic_snowflake_catalog_integration.py
databricks_uniform_sync/logic/snowflake/logic_snowflake_database.py
databricks_uniform_sync/logic/snowflake/logic_snowflake_schema.py
databricks_uniform_sync/logic/snowflake/logic_snowflake_table.py
databricks_uniform_sync/repository/__init__.py
databricks_uniform_sync/repository/databricks/__init__.py
databricks_uniform_sync/repository/databricks/repository_iceberg_catalog.py
databricks_uniform_sync/repository/databricks/repository_unity_catalog.py
databricks_uniform_sync/repository/metadata/__init__.py
databricks_uniform_sync/repository/metadata/metadata_mapping_repository.py
databricks_uniform_sync/repository/snowflake/__init__.py
databricks_uniform_sync/repository/snowflake/repository_snowflake.py
databricks_uniform_sync/repository/snowflake/repository_snowflake_database.py
databricks_uniform_sync/repository/snowflake/repository_snowflake_schema.py
databricks_uniform_sync/utils/__init__.py
databricks_uniform_sync/utils/dbx_to_sf_helpers.py
databricks_uniform_sync-1.1.4.dist-info/licenses/LICENSE
databricks_uniform_sync-1.1.4.dist-info/METADATA
databricks_uniform_sync-1.1.4.dist-info/WHEEL
databricks_uniform_sync-1.1.4.dist-info/top_level.txt
databricks_uniform_sync-1.1.4.dist-info/RECORD
